pyllnu/__init__.py
pyllnu/constants.py
pyllnu/dhcp.py
pyllnu/eth.py
pyllnu/exceptions.py
pyllnu/icmp.py
pyllnu/ipv4.py
pyllnu/ipv6.py
pyllnu/parser.py
pyllnu/struct_ancestor.py
pyllnu/tcp.py
pyllnu/udp.py
pyllnu/util.py
pyllnu-0.2.1.dist-info/LICENSE
pyllnu-0.2.1.dist-info/METADATA
pyllnu-0.2.1.dist-info/WHEEL
pyllnu-0.2.1.dist-info/RECORD
