Metadata-Version: 2.1
Name: pyllnu
Version: 0.2.1
Summary: Low-level network utilities. Interact with low-level sockets easily.
Home-page: https://gitlab.com/debemdeboas/python-low-level-network-utils
License: MIT
Author: Rafael de Bem
Author-email: debemrafael@gmail.com
Maintainer: Rafael de Bem
Maintainer-email: debemrafael@gmail.com
Requires-Python: >=3.9
Classifier: License :: OSI Approved :: MIT License
Classifier: Programming Language :: Python :: 3
Classifier: Programming Language :: Python :: 3.9
Classifier: Programming Language :: Python :: 3.10
Classifier: Programming Language :: Python :: 3.11
Requires-Dist: netifaces (>=0.11.0,<0.12.0)
Project-URL: Repository, https://gitlab.com/debemdeboas/python-low-level-network-utils
